trigseries/__init__.py
trigseries/_types.py
trigseries/core.py
trigseries/utils.py
trigseries-0.1.0.dist-info/licenses/LICENSE
trigseries-0.1.0.dist-info/METADATA
trigseries-0.1.0.dist-info/WHEEL
trigseries-0.1.0.dist-info/top_level.txt
trigseries-0.1.0.dist-info/RECORD
