Metadata-Version: 2.4
Name: trigseries
Version: 0.1.0
Summary: Pure Python implementation of transcendental functions using Taylor/Maclaurin series
Author-email: julin <jl4025@ic.ac.uk>
License: MIT
Project-URL: Homepage, https://github.com/julin/trigseries
Project-URL: Repository, https://github.com/julin/trigseries
Project-URL: Issues, https://github.com/julin/trigseries/issues
Keywords: mathematics,series,trigonometry,exponential,educational
Classifier: Development Status :: 3 - Alpha
Classifier: Intended Audience :: Education
Classifier: Intended Audience :: Science/Research
Classifier: License :: OSI Approved :: MIT License
Classifier: Programming Language :: Python :: 3
Classifier: Programming Language :: Python :: 3.11
Classifier: Programming Language :: Python :: 3.12
Classifier: Programming Language :: Python :: 3.13
Classifier: Topic :: Scientific/Engineering :: Mathematics
Classifier: Topic :: Education
Requires-Python: >=3.11
License-File: LICENSE
Provides-Extra: dev
Requires-Dist: pytest>=7.4; extra == "dev"
Requires-Dist: pytest-cov>=4.1; extra == "dev"
Requires-Dist: ruff>=0.5; extra == "dev"
Requires-Dist: black>=24.4; extra == "dev"
Requires-Dist: flake8>=7.0; extra == "dev"
Provides-Extra: docs
Requires-Dist: sphinx>=7.0; extra == "docs"
Requires-Dist: sphinx-autodoc-typehints>=1.25; extra == "docs"
Dynamic: license-file
